cascaded_heat_merit_order/__init__.py
cascaded_heat_merit_order/dhs.py
cascaded_heat_merit_order/energy_converters.py
cascaded_heat_merit_order/factory.py
cascaded_heat_merit_order/factory_decoder.py
cascaded_heat_merit_order/factory_encoder.py
cascaded_heat_merit_order/fuel.py
cascaded_heat_merit_order/location.py
cascaded_heat_merit_order/merits.py
cascaded_heat_merit_order/network_connectors.py
cascaded_heat_merit_order/networks.py
cascaded_heat_merit_order/utils.py
cascaded_heat_merit_order-0.13.dist-info/LICENSE
cascaded_heat_merit_order-0.13.dist-info/METADATA
cascaded_heat_merit_order-0.13.dist-info/WHEEL
cascaded_heat_merit_order-0.13.dist-info/top_level.txt
cascaded_heat_merit_order-0.13.dist-info/RECORD
