Metadata-Version: 2.1
Name: cascaded-heat-merit-order
Version: 0.13
Summary: Tool for calculating a factory-wide merit order of heat-flows of industrial energy systems.
Author-email: Jan Niklas Scherff <jannik@scherff.eu>
Project-URL: Homepage, https://github.com/GaGandalf/cascaded-heat-merit-order
Classifier: Programming Language :: Python :: 3
Classifier: License :: OSI Approved :: MIT License
Classifier: Operating System :: OS Independent
Requires-Python: >=3.7
License-File: LICENSE
